Metadata-Version: 2.1
Name: django-xworkflows
Version: 1.0.0
Summary: A django app enabling Django models to use xworkflows.
Home-page: http://github.com/rbarrois/django_xworkflows
Author: Raphaël Barrois
Author-email: raphael.barrois+django_xworkflows@polytechnique.org
License: BSD
Download-URL: http://pypi.python.org/pypi/django-xworkflows/
Keywords: django workflow state machine automaton
Platform: UNKNOWN
Classifier: Development Status :: 5 - Production/Stable
Classifier: Intended Audience :: Developers
Classifier: License :: OSI Approved :: BSD License
Classifier: Topic :: Software Development :: Libraries :: Python Modules
Classifier: Operating System :: OS Independent
Classifier: Framework :: Django :: 1.11
Classifier: Framework :: Django :: 2.0
Classifier: Framework :: Django :: 2.1
Classifier: Framework :: Django :: 2.2
Classifier: Framework :: Django :: 3.0
Classifier: Programming Language :: Python
Classifier: Programming Language :: Python :: 3
Classifier: Programming Language :: Python :: 3.4
Classifier: Programming Language :: Python :: 3.5
Classifier: Programming Language :: Python :: 3.6
Classifier: Programming Language :: Python :: 3.7
Requires-Dist: Django (>=1.11)
Requires-Dist: xworkflows
